odoo/addons/ddmrp_report_part_flow_index/README.rst
odoo/addons/ddmrp_report_part_flow_index/__init__.py
odoo/addons/ddmrp_report_part_flow_index/__manifest__.py
odoo/addons/ddmrp_report_part_flow_index/i18n/ddmrp_report_part_flow_index.pot
odoo/addons/ddmrp_report_part_flow_index/i18n/it.po
odoo/addons/ddmrp_report_part_flow_index/models/__init__.py
odoo/addons/ddmrp_report_part_flow_index/models/ddmrp_flow_index_group.py
odoo/addons/ddmrp_report_part_flow_index/models/stock_buffer.py
odoo/addons/ddmrp_report_part_flow_index/readme/CONFIGURE.md
odoo/addons/ddmrp_report_part_flow_index/readme/CONTRIBUTORS.md
odoo/addons/ddmrp_report_part_flow_index/readme/DESCRIPTION.md
odoo/addons/ddmrp_report_part_flow_index/readme/HISTORY.md
odoo/addons/ddmrp_report_part_flow_index/readme/ROADMAP.md
odoo/addons/ddmrp_report_part_flow_index/readme/USAGE.md
odoo/addons/ddmrp_report_part_flow_index/reports/__init__.py
odoo/addons/ddmrp_report_part_flow_index/reports/report_ddmrp_part_plan_flow_index.py
odoo/addons/ddmrp_report_part_flow_index/reports/report_ddmrp_part_plan_flow_index_views.xml
odoo/addons/ddmrp_report_part_flow_index/security/ir.model.access.csv
odoo/addons/ddmrp_report_part_flow_index/security/report_ddmrp_part_plan_flow_index_security.xml
odoo/addons/ddmrp_report_part_flow_index/static/description/icon.png
odoo/addons/ddmrp_report_part_flow_index/static/description/index.html
odoo/addons/ddmrp_report_part_flow_index/tests/__init__.py
odoo/addons/ddmrp_report_part_flow_index/tests/test_ddmrp_report_part_flow_index.py
odoo/addons/ddmrp_report_part_flow_index/views/ddmrp_flow_index_group_views.xml
odoo/addons/ddmrp_report_part_flow_index/views/stock_buffer_view.xml
odoo_addon_ddmrp_report_part_flow_index-18.0.1.0.0.2.dist-info/METADATA
odoo_addon_ddmrp_report_part_flow_index-18.0.1.0.0.2.dist-info/WHEEL
odoo_addon_ddmrp_report_part_flow_index-18.0.1.0.0.2.dist-info/top_level.txt
odoo_addon_ddmrp_report_part_flow_index-18.0.1.0.0.2.dist-info/RECORD
